socketshelpone/__init__.py
socketshelpone/bar.py
socketshelpone/barh.py
socketshelpone/csv.py
socketshelpone/csvbar.py
socketshelpone/download.py
socketshelpone/equal.py
socketshelpone/frequent.py
socketshelpone/hindi.py
socketshelpone/icmp.py
socketshelpone/label.py
socketshelpone/largest.py
socketshelpone/max.py
socketshelpone/normal.py
socketshelpone/profile.py
socketshelpone/search.py
socketshelpone/sort.py
socketshelpone/students.py
socketshelpone/tcp.py
socketshelpone/three.py
socketshelpone/udp.py
socketshelpone-0.0.1.dist-info/LICENSE
socketshelpone-0.0.1.dist-info/METADATA
socketshelpone-0.0.1.dist-info/WHEEL
socketshelpone-0.0.1.dist-info/top_level.txt
socketshelpone-0.0.1.dist-info/RECORD
